ctao_qualpipe_webapp-0.2.0.dist-info/licenses/LICENSE
qualpipe_webapp/__init__.py
qualpipe_webapp/_version.py
qualpipe_webapp/version.py
qualpipe_webapp/backend/.dockerignore
qualpipe_webapp/backend/Dockerfile
qualpipe_webapp/backend/__init__.py
qualpipe_webapp/backend/main.py
qualpipe_webapp/backend/backends/__init__.py
qualpipe_webapp/backend/backends/base.py
qualpipe_webapp/backend/backends/factory.py
qualpipe_webapp/backend/backends/file_backend.py
qualpipe_webapp/backend/codegen/__init__.py
qualpipe_webapp/backend/codegen/generate_data_models.py
qualpipe_webapp/backend/tests/__init__.py
qualpipe_webapp/backend/tests/conftest.py
qualpipe_webapp/backend/tests/test_file_backend.py
qualpipe_webapp/backend/tests/test_generate_data_models.py
qualpipe_webapp/backend/tests/test_hdf5_extraction.py
qualpipe_webapp/backend/tests/test_main.py
qualpipe_webapp/backend/tests/test_stage_dev_data.py
qualpipe_webapp/backend/tests/test_telescope_parameter_validation.py
qualpipe_webapp/frontend/.dockerignore
qualpipe_webapp/frontend/Dockerfile
qualpipe_webapp/frontend/__init__.py
qualpipe_webapp/frontend/main.py
qualpipe_webapp/frontend/scripts/generateSchema.js
qualpipe_webapp/frontend/static/data_schema_cameraview.yaml
qualpipe_webapp/frontend/static/data_schema_histogram1d.yaml
qualpipe_webapp/frontend/static/data_schema_scatterplot.yaml
qualpipe_webapp/frontend/static/template_metadata_schema.yaml
qualpipe_webapp/frontend/static/cameraConfig/lst_pixels_mapping_no_order.txt
qualpipe_webapp/frontend/static/css/_color.scss
qualpipe_webapp/frontend/static/css/badger.css
qualpipe_webapp/frontend/static/css/badger.scss
qualpipe_webapp/frontend/static/css/cameraview.css
qualpipe_webapp/frontend/static/css/cameraview.scss
qualpipe_webapp/frontend/static/css/footer.css
qualpipe_webapp/frontend/static/css/footer.scss
qualpipe_webapp/frontend/static/css/histogram1d.css
qualpipe_webapp/frontend/static/css/histogram1d.scss
qualpipe_webapp/frontend/static/css/scatterPlot.css
qualpipe_webapp/frontend/static/css/scatterPlot.scss
ctao_qualpipe_webapp-0.2.0.dist-info/METADATA
ctao_qualpipe_webapp-0.2.0.dist-info/WHEEL
ctao_qualpipe_webapp-0.2.0.dist-info/entry_points.txt
ctao_qualpipe_webapp-0.2.0.dist-info/top_level.txt
ctao_qualpipe_webapp-0.2.0.dist-info/RECORD
