Metadata-Version: 2.4
Name: ctao-qualpipe-webapp
Version: 0.2.0
Summary: CTAO DPPS QualPipe Web Application
Author-email: Matteo Balbo <matteo.balbo@cta-consortium.org>, Mykhailo Dalchenko <mykhailo.dalchenko@cta-consortium.org>
License-Expression: BSD-3-Clause
Project-URL: repository, https://gitlab.cta-observatory.org/cta-computing/dpps/qualpipe/qualpipe-webapp
Project-URL: documentation, http://cta-computing.gitlab-pages.cta-observatory.org/dpps/qualpipe/qualpipe-webapp
Requires-Python: >=3.12
License-File: LICENSE
Requires-Dist: fastapi
Requires-Dist: uvicorn[standard]
Requires-Dist: ctao-qualpipe
Requires-Dist: pydantic>=2.0
Requires-Dist: pyyaml
Requires-Dist: traitlets
Requires-Dist: numpy
Requires-Dist: numba
Requires-Dist: h5py>=3.0
Requires-Dist: hdf5plugin
Requires-Dist: httpx
Provides-Extra: frontend
Requires-Dist: jinja2; extra == "frontend"
Requires-Dist: libsass; extra == "frontend"
Provides-Extra: test
Requires-Dist: pytest; extra == "test"
Requires-Dist: pytest-cov; extra == "test"
Requires-Dist: httpx; extra == "test"
Requires-Dist: pytest-requirements; extra == "test"
Requires-Dist: playwright; extra == "test"
Requires-Dist: ctao-qualpipe-webapp[frontend]; extra == "test"
Provides-Extra: doc
Requires-Dist: sphinx; extra == "doc"
Requires-Dist: numpydoc; extra == "doc"
Requires-Dist: ctao-sphinx-theme~=0.1.2; extra == "doc"
Requires-Dist: sphinx-changelog; extra == "doc"
Requires-Dist: ctao-qualpipe-webapp[frontend]; extra == "doc"
Requires-Dist: sphinx_copybutton; extra == "doc"
Provides-Extra: webdev
Requires-Dist: watchdog; extra == "webdev"
Provides-Extra: dev
Requires-Dist: setuptools_scm; extra == "dev"
Requires-Dist: towncrier; extra == "dev"
Requires-Dist: ruff; extra == "dev"
Requires-Dist: pip-tools>=7.1; extra == "dev"
Requires-Dist: ctao-qualpipe-webapp[test,webdev]; extra == "dev"
Provides-Extra: all
Requires-Dist: ctao-qualpipe-webapp[dev,doc,frontend,test]; extra == "all"
Dynamic: license-file
